sysinit/__init__.py
sysinit/cli.py
sysinit/utils.py
sysinit/core/__init__.py
sysinit/core/command.py
sysinit/core/command_manager.py
sysinit/core/logger.py
sysinit/core/unit.py
sysinit/core/unit_manager.py
sysinit/tests/test_command.py
sysinit/tests/test_command_engine.py
sysinit/tests/test_unit.py
sysinit/tests/test_unit_manager.py
sysinit-1.0.2.dist-info/licenses/LICENSE
sysinit-1.0.2.dist-info/METADATA
sysinit-1.0.2.dist-info/WHEEL
sysinit-1.0.2.dist-info/entry_points.txt
sysinit-1.0.2.dist-info/top_level.txt
sysinit-1.0.2.dist-info/RECORD
