Metadata-Version: 2.4
Name: sysinit
Version: 1.0.2
Summary: A lightweight Python library for managing systemd service units via YAML configuration, with an interactive terminal.
Author: Nitin Sharma
License: MIT
Project-URL: Homepage, https://github.com/foo290/sysinit
Keywords: systemd,service,manager,init,process,daemon,linux,yaml,repl,terminal,cli
Classifier: Development Status :: 3 - Alpha
Classifier: Environment :: Console
Classifier: Intended Audience :: Developers
Classifier: Intended Audience :: System Administrators
Classifier: License :: OSI Approved :: MIT License
Classifier: Operating System :: POSIX :: Linux
Classifier: Programming Language :: Python :: 3
Classifier: Programming Language :: Python :: 3.8
Classifier: Programming Language :: Python :: 3.9
Classifier: Programming Language :: Python :: 3.10
Classifier: Programming Language :: Python :: 3.11
Classifier: Programming Language :: Python :: 3.12
Classifier: Topic :: System :: Systems Administration
Classifier: Topic :: Software Development :: Libraries :: Python Modules
Classifier: Topic :: Terminals :: Terminal Emulators/X Terminals
Requires-Python: >=3.9
License-File: LICENSE
Requires-Dist: pytest-mock>=3.14.0
Requires-Dist: pyyaml>=6.0.2
Requires-Dist: typer[all]>=0.9.0
Requires-Dist: ipython>=7.0
Provides-Extra: dev
Requires-Dist: black>=25.1.0; extra == "dev"
Requires-Dist: pytest>=8.3.5; extra == "dev"
Requires-Dist: build; extra == "dev"
Requires-Dist: twine; extra == "dev"
Requires-Dist: ipython>=7.0; extra == "dev"
Dynamic: license-file
